pyquestionit/__init__.py
pyquestionit/client.py
pyquestionit/config.py
pyquestionit/test.py
pyquestionit-1.0.1.dist-info/LICENSE.txt
pyquestionit-1.0.1.dist-info/METADATA
pyquestionit-1.0.1.dist-info/WHEEL
pyquestionit-1.0.1.dist-info/top_level.txt
pyquestionit-1.0.1.dist-info/RECORD
