Metadata-Version: 2.1
Name: pyquestionit
Version: 1.0.1
Summary: Official client for QuestionIt.space API
Home-page: https://github.com/alkihis/pyquestionit
Author: Alkihis
Author-email: beranger.louis.bio@gmail.com
License: MIT
Keywords: questionit,api client
Platform: UNKNOWN
Classifier: Development Status :: 3 - Alpha
Classifier: Intended Audience :: Developers
Classifier: License :: OSI Approved :: MIT License
Classifier: Programming Language :: Python :: 3.6
Classifier: Programming Language :: Python :: 3.7
Classifier: Programming Language :: Python :: 3.8
Classifier: Programming Language :: Python :: 3.9
Requires-Dist: requests
Requires-Dist: requests-toolbelt
